setup.py
a_oder.egg-info/PKG-INFO
a_oder.egg-info/SOURCES.txt
a_oder.egg-info/dependency_links.txt
a_oder.egg-info/top_level.txt
ha_oder/__init__.py
ha_oder/a_oder.py