Metadata-Version: 2.1
Name: a_oder
Version: 8.0.0
Summary: telegram 
Author: Programmer king 
Classifier: Programming Language :: Python :: 3
Classifier: Operating System :: OS Independent
Classifier: License :: OSI Approved :: MIT License
